odoo10_addon_account_invoice_merge_operating_unit-10.0.1.0.0-py2.7-nspkg.pth
odoo/addons/account_invoice_merge_operating_unit/README.rst
odoo/addons/account_invoice_merge_operating_unit/__init__.py
odoo/addons/account_invoice_merge_operating_unit/__manifest__.py
odoo/addons/account_invoice_merge_operating_unit/models/__init__.py
odoo/addons/account_invoice_merge_operating_unit/models/account_invoice.py
odoo/addons/account_invoice_merge_operating_unit/tests/__init__.py
odoo/addons/account_invoice_merge_operating_unit/tests/test_account_invoice_merge_operating_unit.py
odoo/addons/account_invoice_merge_operating_unit/wizard/__init__.py
odoo/addons/account_invoice_merge_operating_unit/wizard/invoice_merge.py
odoo/addons/account_invoice_merge_operating_unit/wizard/invoice_merge_view.xml
odoo10_addon_account_invoice_merge_operating_unit-10.0.1.0.0.dist-info/DESCRIPTION.rst
odoo10_addon_account_invoice_merge_operating_unit-10.0.1.0.0.dist-info/METADATA
odoo10_addon_account_invoice_merge_operating_unit-10.0.1.0.0.dist-info/RECORD
odoo10_addon_account_invoice_merge_operating_unit-10.0.1.0.0.dist-info/WHEEL
odoo10_addon_account_invoice_merge_operating_unit-10.0.1.0.0.dist-info/metadata.json
odoo10_addon_account_invoice_merge_operating_unit-10.0.1.0.0.dist-info/namespace_packages.txt
odoo10_addon_account_invoice_merge_operating_unit-10.0.1.0.0.dist-info/top_level.txt
